{
  "gitSyncId": "68b614bc2095503390660a2c_0f0868b2-15b3-4f46-8d4c-088c7e4486f0",
  "id": "Main_JSCategoryDialog.askDelete",
  "pluginId": "js-plugin",
  "pluginType": "JS",
  "unpublishedAction": {
    "actionConfiguration": {
      "encodeParamsToggle": true,
      "jsArguments": [],
      "paginationType": "NONE",
      "timeoutInMillisecond": 10000
    },
    "collectionId": "Main_JSCategoryDialog",
    "confirmBeforeExecute": false,
    "datasource": {
      "isAutoGenerated": false,
      "name": "UNUSED_DATASOURCE",
      "pluginId": "js-plugin"
    },
    "dynamicBindingPathList": [
      {
        "key": "body"
      }
    ],
    "fullyQualifiedName": "JSCategoryDialog.askDelete",
    "name": "askDelete",
    "pageId": "Main",
    "runBehaviour": "MANUAL",
    "userSetOnLoad": false
  }
}